portkey_ai/__init__.py
portkey_ai/_portkey_scripts.py
portkey_ai/py.typed
portkey_ai/version.py
portkey_ai/_vendor/__init__.py
portkey_ai/_vendor/openai/__init__.py
portkey_ai/_vendor/openai/__main__.py
portkey_ai/_vendor/openai/_base_client.py
portkey_ai/_vendor/openai/_client.py
portkey_ai/_vendor/openai/_compat.py
portkey_ai/_vendor/openai/_constants.py
portkey_ai/_vendor/openai/_exceptions.py
portkey_ai/_vendor/openai/_files.py
portkey_ai/_vendor/openai/_legacy_response.py
portkey_ai/_vendor/openai/_models.py
portkey_ai/_vendor/openai/_module_client.py
portkey_ai/_vendor/openai/_qs.py
portkey_ai/_vendor/openai/_resource.py
portkey_ai/_vendor/openai/_response.py
portkey_ai/_vendor/openai/_streaming.py
portkey_ai/_vendor/openai/_types.py
portkey_ai/_vendor/openai/_version.py
portkey_ai/_vendor/openai/pagination.py
portkey_ai/_vendor/openai/py.typed
portkey_ai/_vendor/openai/version.py
portkey_ai/_vendor/openai/_extras/__init__.py
portkey_ai/_vendor/openai/_extras/_common.py
portkey_ai/_vendor/openai/_extras/numpy_proxy.py
portkey_ai/_vendor/openai/_extras/pandas_proxy.py
portkey_ai/_vendor/openai/_extras/sounddevice_proxy.py
portkey_ai/_vendor/openai/_utils/__init__.py
portkey_ai/_vendor/openai/_utils/_compat.py
portkey_ai/_vendor/openai/_utils/_datetime_parse.py
portkey_ai/_vendor/openai/_utils/_logs.py
portkey_ai/_vendor/openai/_utils/_proxy.py
portkey_ai/_vendor/openai/_utils/_reflection.py
portkey_ai/_vendor/openai/_utils/_resources_proxy.py
portkey_ai/_vendor/openai/_utils/_streams.py
portkey_ai/_vendor/openai/_utils/_sync.py
portkey_ai/_vendor/openai/_utils/_transform.py
portkey_ai/_vendor/openai/_utils/_typing.py
portkey_ai/_vendor/openai/_utils/_utils.py
portkey_ai/_vendor/openai/cli/__init__.py
portkey_ai/_vendor/openai/cli/_cli.py
portkey_ai/_vendor/openai/cli/_errors.py
portkey_ai/_vendor/openai/cli/_models.py
portkey_ai/_vendor/openai/cli/_progress.py
portkey_ai/_vendor/openai/cli/_utils.py
portkey_ai/_vendor/openai/cli/_api/__init__.py
portkey_ai-2.0.4.dist-info/licenses/LICENSE
portkey_ai-2.0.4.dist-info/METADATA
portkey_ai-2.0.4.dist-info/WHEEL
portkey_ai-2.0.4.dist-info/entry_points.txt
portkey_ai-2.0.4.dist-info/top_level.txt
portkey_ai-2.0.4.dist-info/zip-safe
portkey_ai-2.0.4.dist-info/RECORD
