Metadata-Version: 2.4
Name: portkey-ai
Version: 2.0.4
Summary: Python client library for the Portkey API
Home-page: https://github.com/Portkey-AI/portkey-python-sdk
Author: Portkey.ai
Author-email: support@portkey.ai
License: MIT License
Classifier: Programming Language :: Python :: 3
Classifier: Operating System :: OS Independent
Requires-Python: >=3.8
License-File: LICENSE
Requires-Dist: httpx
Requires-Dist: typing_extensions<5.0,>=4.7.1
Requires-Dist: pydantic>=1.10.8
Requires-Dist: anyio<5,>=3.5.0
Requires-Dist: distro<2,>=1.7.0
Requires-Dist: sniffio
Requires-Dist: cached-property
Requires-Dist: tqdm>4
Requires-Dist: types-requests
Requires-Dist: jiter<1,>=0.4.0
Provides-Extra: dev
Requires-Dist: mypy<2.0,>=0.991; extra == "dev"
Requires-Dist: black==23.7.0; extra == "dev"
Requires-Dist: pytest==7.4.2; extra == "dev"
Requires-Dist: python-dotenv==1.0.0; extra == "dev"
Requires-Dist: ruff==0.0.292; extra == "dev"
Requires-Dist: pytest-asyncio==0.23.5; extra == "dev"
Provides-Extra: langchain-callback
Requires-Dist: langchain-core; extra == "langchain-callback"
Provides-Extra: llama-index-callback
Requires-Dist: llama-index; extra == "llama-index-callback"
Provides-Extra: instrumentation
Requires-Dist: opentelemetry-sdk<2.0,>=1.29.0; extra == "instrumentation"
Requires-Dist: opentelemetry-instrumentation<1.0,>=0.50b0; extra == "instrumentation"
Requires-Dist: wrapt<2.0,>=1.17.0; extra == "instrumentation"
Provides-Extra: strands
Requires-Dist: strands-agents>=0.0.0; extra == "strands"
Provides-Extra: adk
Requires-Dist: google-adk; extra == "adk"
Requires-Dist: google-genai; extra == "adk"
Dynamic: license-file
